README.rst
setup.cfg
setup.py
./__init__.py
./product.py
./product.xml
./report.py
./tryton.cfg
./tests/__init__.py
./tests/test_views_depends.py
./view/product_form.xml
./view/product_warehouse_location_list.xml
fio_product_warehouse_location.egg-info/PKG-INFO
fio_product_warehouse_location.egg-info/SOURCES.txt
fio_product_warehouse_location.egg-info/dependency_links.txt
fio_product_warehouse_location.egg-info/entry_points.txt
fio_product_warehouse_location.egg-info/not-zip-safe
fio_product_warehouse_location.egg-info/requires.txt
fio_product_warehouse_location.egg-info/top_level.txt