Metadata-Version: 1.1
Name: fio-product-warehouse-location
Version: 3.4.0.2
Summary: Location of products in a warehouse
Home-page: http://www.fulfil.io/
Author: Fulfil.IO Inc.
Author-email: info@fulfil.io
License: BSD
Platform: UNKNOWN
Classifier: Development Status :: 4 - Beta
Classifier: Environment :: Plugins
Classifier: Intended Audience :: Developers
Classifier: License :: OSI Approved :: BSD License
Classifier: Natural Language :: English
Classifier: Operating System :: OS Independent
Classifier: Programming Language :: Python
Classifier: Framework :: Tryton
Classifier: Topic :: Office/Business
